lock/__init__.py
lock/locker.py
py_heart_locker-1.1.dist-info/licenses/LICENSE.txt
py_heart_locker-1.1.dist-info/METADATA
py_heart_locker-1.1.dist-info/WHEEL
py_heart_locker-1.1.dist-info/top_level.txt
py_heart_locker-1.1.dist-info/RECORD
