Metadata-Version: 2.4
Name: py-heart-locker
Version: 1.1
Summary: Python process locker to avoid repeatedly executing the same script at the same time
Home-page: https://github.com/EXP-Codes/py-heart-locker
Author: EXP
Author-email: 289065406@qq.com
Project-URL: Bug Reports, https://github.com/EXP-Codes/py-heart-locker/issues
Project-URL: Funding, https://github.com/EXP-Codes/py-heart-locker/blob/master/imgs/donate-alipay.png
Project-URL: Say Thanks!, https://github.com/EXP-Codes/py-heart-locker/blob/master/imgs/donate-wechat.png
Project-URL: Source, https://github.com/EXP-Codes/py-heart-locker/
Keywords: locker,lock
Classifier: Development Status :: 3 - Alpha
Classifier: Intended Audience :: Developers
Classifier: Topic :: Software Development :: Build Tools
Classifier: License :: OSI Approved :: MIT License
Classifier: Programming Language :: Python :: 3
Classifier: Programming Language :: Python :: 3.5
Classifier: Programming Language :: Python :: 3.6
Classifier: Programming Language :: Python :: 3.7
Classifier: Programming Language :: Python :: 3.8
Classifier: Programming Language :: Python :: 3 :: Only
Requires-Python: >=3.5, <4
License-File: LICENSE.txt
Provides-Extra: dev
Requires-Dist: check-manifest; extra == "dev"
Provides-Extra: test
Requires-Dist: coverage; extra == "test"
Dynamic: author
Dynamic: author-email
Dynamic: classifier
Dynamic: description
Dynamic: description-content-type
Dynamic: home-page
Dynamic: keywords
Dynamic: license-file
Dynamic: project-url
Dynamic: provides-extra
Dynamic: requires-python
Dynamic: summary
